dunky/__init__.py
dunky/__main__.py
dunky/build.py
dunky/config.py
dunky/delta.py
dunky/display.py
dunky/dunky_kernel.py
dunky/store.py
dunky/threading.py
dunky/unity.py
dunky-0.3.0.data/data/share/jupyter/kernels/dunky/kernel.json
dunky-0.3.0.dist-info/METADATA
dunky-0.3.0.dist-info/WHEEL
dunky-0.3.0.dist-info/licenses/LICENSE
dunky-0.3.0.dist-info/RECORD
