Metadata-Version: 2.4
Name: dunky
Version: 0.3.0
Summary: A Jupyter Kernel for DuckDB with Unity Catalog
License-File: LICENSE
Requires-Python: >=3.11
Requires-Dist: duckdb<1.3,>=1
Requires-Dist: ipykernel<7,>=6
Requires-Dist: itables>=2.4.0
Requires-Dist: pandas<3,>=2
Requires-Dist: requests<3,>=2
Requires-Dist: tabulate==0.9.0
Provides-Extra: delta
Requires-Dist: deltalake>=0.18.2; extra == 'delta'
Requires-Dist: pyarrow-unity>=0.1.0; extra == 'delta'
